Metadata-Version: 2.1
Name: hass-desktop-sensor
Version: 1.0.1
Summary: Desktop activity sensor for Home Assistant
Home-page: https://github.com/ShellCode33/HASS-Desktop-Sensor
Author: ShellCode
Author-email: shellcode33@protonmail.ch
License: MIT
Keywords: home assistant desktop sensor idle activity
Platform: UNKNOWN
Classifier: Programming Language :: Python :: 3.6
Classifier: Programming Language :: Python :: 3.7
Classifier: Programming Language :: Python :: 3.8
Classifier: Programming Language :: Python :: 3.9
Classifier: Programming Language :: Python :: 3.10
Classifier: License :: OSI Approved :: MIT License
Classifier: Operating System :: POSIX :: Linux
Requires-Python: >=3.6
License-File: LICENSE
